pybmr/__init__.py
tests/__init__.py
tests/conftest.py
tests/test_pybmr.py
pybmr-0.7.2.dist-info/LICENSE.md
pybmr-0.7.2.dist-info/METADATA
pybmr-0.7.2.dist-info/WHEEL
pybmr-0.7.2.dist-info/top_level.txt
pybmr-0.7.2.dist-info/RECORD
