Metadata-Version: 2.1
Name: pybmr
Version: 0.7.2
Summary: Python library for communication with BMR HC64 Heating Controller units
Home-page: https://github.com/slesinger/pybmr
Author: Honza Slesinger
Author-email: slesinger@gmail.com
Classifier: Programming Language :: Python :: 3
Classifier: License :: OSI Approved :: Apache Software License
Classifier: Operating System :: OS Independent
License-File: LICENSE.md
Requires-Dist: cachetools (==4.2.4)
Requires-Dist: certifi (==2021.10.8)
Requires-Dist: charset-normalizer (==2.0.9)
Requires-Dist: idna (==3.3)
Requires-Dist: requests (==2.28.0)
Requires-Dist: requests-toolbelt (==0.9.1)
Requires-Dist: urllib3 (==1.26.14)
